{
    "openapi": "3.0.0",
    "info": {
        "title": "My API",
        "description": "API documentation using Swagger",
        "version": "1.0.0"
    },
    "paths": {
        "/api/galleries": {},
        "/api/otzivis": {},
        "/api/posts": {},
        "/api/services": {},
        "/api/zayavkas": {
            "post": {
                "tags": [
                    "Zayavka"
                ],
                "summary": "Create a new zayavka",
                "operationId": "0cba6c1cbc98a2898f523c7f7cfe37f6",
                "requestBody": {
                    "required": true,
                    "content": {
                        "application/json": {
                            "schema": {
                                "$ref": "#/components/schemas/Zayavka"
                            }
                        }
                    }
                },
                "responses": {
                    "201": {
                        "description": "Created"
                    }
                }
            }
        },
        "/api/banners": {
            "get": {
                "summary": "Get list of galleries",
                "operationId": "87ccfb3533d0f233329e6cc3620e2e2c",
                "responses": {
                    "200": {
                        "description": "A list of galleries"
                    }
                }
            }
        },
        "/api/banners/{id}": {
            "get": {
                "summary": "Get a gallery by ID",
                "operationId": "d507ea8cbd697940f0abbf8fa621b0b7",
                "parameters": [
                    {
                        "name": "id",
                        "in": "path",
                        "required": true,
                        "schema": {
                            "type": "integer"
                        }
                    }
                ],
                "responses": {
                    "200": {
                        "description": "A gallery"
                    },
                    "404": {
                        "description": "Gallery not found"
                    }
                }
            }
        },
        "/api/partners": {
            "get": {
                "summary": "Get list of reviews",
                "operationId": "d2f5b1ee8f50962d7ef84d5b0eb3f875",
                "responses": {
                    "200": {
                        "description": "A list of reviews"
                    }
                }
            }
        },
        "/api/partners/{id}": {
            "get": {
                "summary": "Get a review by ID",
                "operationId": "d84bed521ab02de544d86f9015755be2",
                "parameters": [
                    {
                        "name": "id",
                        "in": "path",
                        "required": true,
                        "schema": {
                            "type": "integer"
                        }
                    }
                ],
                "responses": {
                    "200": {
                        "description": "A review"
                    },
                    "404": {
                        "description": "Review not found"
                    }
                }
            }
        },
        "/api/posts/": {
            "get": {
                "summary": "Get list of reviews",
                "operationId": "d3736e03cd3d1c5c7b67db654db0d30e",
                "responses": {
                    "200": {
                        "description": "A list of reviews"
                    }
                }
            }
        },
        "/api/post/category": {
            "get": {
                "summary": "Get products by category",
                "operationId": "85b53ed93099a2d7cc216b1790639b0e",
                "parameters": [
                    {
                        "name": "category_id",
                        "in": "query",
                        "required": true,
                        "schema": {
                            "type": "string"
                        }
                    }
                ],
                "responses": {
                    "200": {
                        "description": "A list of products"
                    },
                    "404": {
                        "description": "Category not found"
                    }
                }
            }
        },
        "/api/posts/{id}": {
            "get": {
                "summary": "Get a review by ID",
                "operationId": "142b5adb0520cca80cedfe09d9298332",
                "parameters": [
                    {
                        "name": "id",
                        "in": "path",
                        "required": true,
                        "schema": {
                            "type": "integer"
                        }
                    }
                ],
                "responses": {
                    "200": {
                        "description": "A review"
                    },
                    "404": {
                        "description": "Review not found"
                    }
                }
            }
        },
        "/api/services/": {
            "get": {
                "summary": "Get list of reviews",
                "operationId": "cb005c6a8bfd84ec82203d49034721d4",
                "responses": {
                    "200": {
                        "description": "A list of reviews"
                    }
                }
            }
        },
        "/api/services/{id}": {
            "get": {
                "summary": "Get a review by ID",
                "operationId": "a55ba44f6d80dadcc0547de01492bcfd",
                "parameters": [
                    {
                        "name": "id",
                        "in": "path",
                        "required": true,
                        "schema": {
                            "type": "integer"
                        }
                    }
                ],
                "responses": {
                    "200": {
                        "description": "A review"
                    },
                    "404": {
                        "description": "Review not found"
                    }
                }
            }
        },
        "/api/zayavkas/": {
            "get": {
                "summary": "Get list of reviews",
                "operationId": "878ad7b65f74fac20ef3f3e96d1381a1",
                "responses": {
                    "200": {
                        "description": "A list of reviews"
                    }
                }
            }
        }
    },
    "components": {
        "schemas": {
            "Zayavka": {
                "required": [
                    "first_name",
                    "last_name",
                    "phone_number",
                    "descriptions",
                    "email",
                    "company"
                ],
                "properties": {
                    "id": {
                        "type": "integer",
                        "example": "1"
                    },
                    "first_name": {
                        "type": "string",
                        "example": "John"
                    },
                    "last_name": {
                        "type": "string",
                        "example": "Doe"
                    },
                    "phone_number": {
                        "type": "string",
                        "example": "+123456789"
                    },
                    "descriptions": {
                        "type": "string",
                        "example": "vdfdfvfdv"
                    },
                    "email": {
                        "type": "string",
                        "example": "ndc@gmail.com"
                    },
                    "company": {
                        "type": "string",
                        "example": "NDC"
                    },
                    "created_at": {
                        "type": "string",
                        "format": "date-time"
                    },
                    "updated_at": {
                        "type": "string",
                        "format": "date-time"
                    }
                },
                "type": "object"
            }
        }
    }
}